{
  "matrix": [1, 0, 0, 1, -1341, 0],
  "glyphs": [
    {
      "fontId": 24,
      "color": 4287137928,
      "x": 0,
      "y": 200,
      "size": 220,
      "index": 46
    },
    {
      "fontId": 24,
      "color": 4287137928,
      "x": 165,
      "y": 200,
      "size": 220,
      "index": 47
    },
    {
      "fontId": 24,
      "color": 4287137928,
      "x": 338,
      "y": 200,
      "size": 220,
      "index": 0
    },
    {
      "fontId": 24,
      "color": 4287137928,
      "x": 408,
      "y": 200,
      "size": 220,
      "index": 35
    },
    {
      "fontId": 24,
      "color": 4287137928,
      "x": 562,
      "y": 200,
      "size": 220,
      "index": 41
    },
    {
      "fontId": 24,
      "color": 4287137928,
      "x": 626,
      "y": 200,
      "size": 220,
      "index": 52
    },
    {
      "fontId": 24,
      "color": 4287137928,
      "x": 760,
      "y": 200,
      "size": 220,
      "index": 41
    },
    {
      "fontId": 24,
      "color": 4287137928,
      "x": 825,
      "y": 200,
      "size": 220,
      "index": 58
    },
    {
      "fontId": 24,
      "color": 4287137928,
      "x": 976,
      "y": 200,
      "size": 220,
      "index": 37
    },
    {
      "fontId": 24,
      "color": 4287137928,
      "x": 1115,
      "y": 200,
      "size": 220,
      "index": 46
    },
    {
      "fontId": 24,
      "color": 4287137928,
      "x": 1280,
      "y": 200,
      "size": 220,
      "index": 0
    },
    {
      "fontId": 24,
      "color": 4287137928,
      "x": 1350,
      "y": 200,
      "size": 220,
      "index": 41
    },
    {
      "fontId": 24,
      "color": 4287137928,
      "x": 1415,
      "y": 200,
      "size": 220,
      "index": 51
    },
    {
      "fontId": 24,
      "color": 4287137928,
      "x": 1555,
      "y": 200,
      "size": 220,
      "index": 0
    },
    {
      "fontId": 24,
      "color": 4287137928,
      "x": 1625,
      "y": 200,
      "size": 220,
      "index": 33
    },
    {
      "fontId": 24,
      "color": 4287137928,
      "x": 1775,
      "y": 200,
      "size": 220,
      "index": 44
    },
    {
      "fontId": 24,
      "color": 4287137928,
      "x": 1898,
      "y": 200,
      "size": 220,
      "index": 44
    },
    {
      "fontId": 24,
      "color": 4287137928,
      "x": 2012,
      "y": 200,
      "size": 220,
      "index": 47
    },
    {
      "fontId": 24,
      "color": 4287137928,
      "x": 2185,
      "y": 200,
      "size": 220,
      "index": 55
    },
    {
      "fontId": 24,
      "color": 4287137928,
      "x": 2403,
      "y": 200,
      "size": 220,
      "index": 37
    },
    {
      "fontId": 24,
      "color": 4287137928,
      "x": 2542,
      "y": 200,
      "size": 220,
      "index": 36
    },
    {
      "fontId": 24,
      "color": 4287137928,
      "x": 2711,
      "y": 200,
      "size": 220,
      "index": 0
    },
    {
      "fontId": 24,
      "color": 4287137928,
      "x": 2781,
      "y": 200,
      "size": 220,
      "index": 52
    },
    {
      "fontId": 24,
      "color": 4287137928,
      "x": 2915,
      "y": 200,
      "size": 220,
      "index": 47
    },
    {
      "fontId": 24,
      "color": 4287137928,
      "x": 3089,
      "y": 200,
      "size": 220,
      "index": 0
    },
    {
      "fontId": 24,
      "color": 4287137928,
      "x": 3159,
      "y": 200,
      "size": 220,
      "index": 44
    },
    {
      "fontId": 24,
      "color": 4287137928,
      "x": 3282,
      "y": 200,
      "size": 220,
      "index": 37
    },
    {
      "fontId": 24,
      "color": 4287137928,
      "x": 3421,
      "y": 200,
      "size": 220,
      "index": 33
    },
    {
      "fontId": 24,
      "color": 4287137928,
      "x": 3557,
      "y": 200,
      "size": 220,
      "index": 54
    },
    {
      "fontId": 24,
      "color": 4287137928,
      "x": 3708,
      "y": 200,
      "size": 220,
      "index": 37
    },
    {
      "fontId": 24,
      "color": 4287137928,
      "x": 3848,
      "y": 200,
      "size": 220,
      "index": 0
    },
    {
      "fontId": 24,
      "color": 4287137928,
      "x": 3918,
      "y": 200,
      "size": 220,
      "index": 52
    },
    {
      "fontId": 24,
      "color": 4287137928,
      "x": 4052,
      "y": 200,
      "size": 220,
      "index": 40
    },
    {
      "fontId": 24,
      "color": 4287137928,
      "x": 4218,
      "y": 200,
      "size": 220,
      "index": 37
    },
    {
      "fontId": 24,
      "color": 4287137928,
      "x": 4357,
      "y": 200,
      "size": 220,
      "index": 0
    },
    {
      "fontId": 24,
      "color": 4287137928,
      "x": 4427,
      "y": 200,
      "size": 220,
      "index": 35
    },
    {
      "fontId": 24,
      "color": 4287137928,
      "x": 4581,
      "y": 200,
      "size": 220,
      "index": 41
    },
    {
      "fontId": 24,
      "color": 4287137928,
      "x": 4645,
      "y": 200,
      "size": 220,
      "index": 52
    },
    {
      "fontId": 24,
      "color": 4287137928,
      "x": 4779,
      "y": 200,
      "size": 220,
      "index": 57
    },
    {
      "fontId": 24,
      "color": 4287137928,
      "x": 4914,
      "y": 200,
      "size": 220,
      "index": 0
    },
    {
      "fontId": 24,
      "color": 4287137928,
      "x": 4984,
      "y": 200,
      "size": 220,
      "index": 55
    },
    {
      "fontId": 24,
      "color": 4287137928,
      "x": 5201,
      "y": 200,
      "size": 220,
      "index": 41
    },
    {
      "fontId": 24,
      "color": 4287137928,
      "x": 5265,
      "y": 200,
      "size": 220,
      "index": 52
    },
    {
      "fontId": 24,
      "color": 4287137928,
      "x": 5399,
      "y": 200,
      "size": 220,
      "index": 40
    },
    {
      "fontId": 24,
      "color": 4287137928,
      "x": 5565,
      "y": 200,
      "size": 220,
      "index": 47
    },
    {
      "fontId": 24,
      "color": 4287137928,
      "x": 5739,
      "y": 200,
      "size": 220,
      "index": 53
    },
    {
      "fontId": 24,
      "color": 4287137928,
      "x": 5900,
      "y": 200,
      "size": 220,
      "index": 52
    },
    {
      "fontId": 24,
      "color": 4287137928,
      "x": 6034,
      "y": 200,
      "size": 220,
      "index": 0
    },
    {
      "fontId": 24,
      "color": 4287137928,
      "x": 6104,
      "y": 200,
      "size": 220,
      "index": 48
    },
    {
      "fontId": 24,
      "color": 4287137928,
      "x": 6237,
      "y": 200,
      "size": 220,
      "index": 50
    },
    {
      "fontId": 24,
      "color": 4287137928,
      "x": 6390,
      "y": 200,
      "size": 220,
      "index": 41
    },
    {
      "fontId": 24,
      "color": 4287137928,
      "x": 6455,
      "y": 200,
      "size": 220,
      "index": 47
    },
    {
      "fontId": 24,
      "color": 4287137928,
      "x": 6628,
      "y": 200,
      "size": 220,
      "index": 50
    },
    {
      "fontId": 24,
      "color": 4287137928,
      "x": 6781,
      "y": 200,
      "size": 220,
      "index": 0
    },
    {
      "fontId": 24,
      "color": 4287137928,
      "x": 0,
      "y": 500,
      "size": 220,
      "index": 33
    },
    {
      "fontId": 24,
      "color": 4287137928,
      "x": 150,
      "y": 500,
      "size": 220,
      "index": 53
    },
    {
      "fontId": 24,
      "color": 4287137928,
      "x": 312,
      "y": 500,
      "size": 220,
      "index": 52
    },
    {
      "fontId": 24,
      "color": 4287137928,
      "x": 446,
      "y": 500,
      "size": 220,
      "index": 40
    },
    {
      "fontId": 24,
      "color": 4287137928,
      "x": 612,
      "y": 500,
      "size": 220,
      "index": 47
    },
    {
      "fontId": 24,
      "color": 4287137928,
      "x": 786,
      "y": 500,
      "size": 220,
      "index": 50
    },
    {
      "fontId": 24,
      "color": 4287137928,
      "x": 939,
      "y": 500,
      "size": 220,
      "index": 41
    },
    {
      "fontId": 24,
      "color": 4287137928,
      "x": 1004,
      "y": 500,
      "size": 220,
      "index": 58
    },
    {
      "fontId": 24,
      "color": 4287137928,
      "x": 1155,
      "y": 500,
      "size": 220,
      "index": 33
    },
    {
      "fontId": 24,
      "color": 4287137928,
      "x": 1288,
      "y": 500,
      "size": 220,
      "index": 52
    },
    {
      "fontId": 24,
      "color": 4287137928,
      "x": 1423,
      "y": 500,
      "size": 220,
      "index": 41
    },
    {
      "fontId": 24,
      "color": 4287137928,
      "x": 1488,
      "y": 500,
      "size": 220,
      "index": 47
    },
    {
      "fontId": 24,
      "color": 4287137928,
      "x": 1661,
      "y": 500,
      "size": 220,
      "index": 46
    },
    {
      "fontId": 24,
      "color": 4287137928,
      "x": 1826,
      "y": 500,
      "size": 220,
      "index": 0
    },
    {
      "fontId": 24,
      "color": 4287137928,
      "x": 1896,
      "y": 500,
      "size": 220,
      "index": 33
    },
    {
      "fontId": 24,
      "color": 4287137928,
      "x": 2046,
      "y": 500,
      "size": 220,
      "index": 46
    },
    {
      "fontId": 24,
      "color": 4287137928,
      "x": 2211,
      "y": 500,
      "size": 220,
      "index": 36
    },
    {
      "fontId": 24,
      "color": 4287137928,
      "x": 2380,
      "y": 500,
      "size": 220,
      "index": 0
    },
    {
      "fontId": 24,
      "color": 4287137928,
      "x": 2450,
      "y": 500,
      "size": 220,
      "index": 50
    },
    {
      "fontId": 24,
      "color": 4287137928,
      "x": 2603,
      "y": 500,
      "size": 220,
      "index": 37
    },
    {
      "fontId": 24,
      "color": 4287137928,
      "x": 2742,
      "y": 500,
      "size": 220,
      "index": 33
    },
    {
      "fontId": 24,
      "color": 4287137928,
      "x": 2893,
      "y": 500,
      "size": 220,
      "index": 51
    },
    {
      "fontId": 24,
      "color": 4287137928,
      "x": 3033,
      "y": 500,
      "size": 220,
      "index": 47
    },
    {
      "fontId": 24,
      "color": 4287137928,
      "x": 3206,
      "y": 500,
      "size": 220,
      "index": 46
    },
    {
      "fontId": 24,
      "color": 4287137928,
      "x": 3371,
      "y": 500,
      "size": 220,
      "index": 14
    },
    {
      "fontId": 24,
      "color": 4287137928,
      "x": 3441,
      "y": 500,
      "size": 220,
      "index": 0
    },
    {
      "fontId": 24,
      "color": 4287137928,
      "x": 3511,
      "y": 500,
      "size": 220,
      "index": 0
    },
    {
      "fontId": 24,
      "color": 4287137928,
      "x": 3581,
      "y": 500,
      "size": 220,
      "index": 48
    },
    {
      "fontId": 24,
      "color": 4287137928,
      "x": 3714,
      "y": 500,
      "size": 220,
      "index": 44
    },
    {
      "fontId": 24,
      "color": 4287137928,
      "x": 3836,
      "y": 500,
      "size": 220,
      "index": 37
    },
    {
      "fontId": 24,
      "color": 4287137928,
      "x": 3975,
      "y": 500,
      "size": 220,
      "index": 33
    },
    {
      "fontId": 24,
      "color": 4287137928,
      "x": 4126,
      "y": 500,
      "size": 220,
      "index": 51
    },
    {
      "fontId": 24,
      "color": 4287137928,
      "x": 4266,
      "y": 500,
      "size": 220,
      "index": 37
    },
    {
      "fontId": 24,
      "color": 4287137928,
      "x": 4405,
      "y": 500,
      "size": 220,
      "index": 0
    },
    {
      "fontId": 24,
      "color": 4287137928,
      "x": 4475,
      "y": 500,
      "size": 220,
      "index": 50
    },
    {
      "fontId": 24,
      "color": 4287137928,
      "x": 4628,
      "y": 500,
      "size": 220,
      "index": 37
    },
    {
      "fontId": 24,
      "color": 4287137928,
      "x": 4767,
      "y": 500,
      "size": 220,
      "index": 52
    },
    {
      "fontId": 24,
      "color": 4287137928,
      "x": 4901,
      "y": 500,
      "size": 220,
      "index": 53
    },
    {
      "fontId": 24,
      "color": 4287137928,
      "x": 5062,
      "y": 500,
      "size": 220,
      "index": 50
    },
    {
      "fontId": 24,
      "color": 4287137928,
      "x": 5215,
      "y": 500,
      "size": 220,
      "index": 46
    },
    {
      "fontId": 24,
      "color": 4287137928,
      "x": 5379,
      "y": 500,
      "size": 220,
      "index": 0
    },
    {
      "fontId": 24,
      "color": 4287137928,
      "x": 5449,
      "y": 500,
      "size": 220,
      "index": 52
    },
    {
      "fontId": 24,
      "color": 4287137928,
      "x": 5583,
      "y": 500,
      "size": 220,
      "index": 47
    },
    {
      "fontId": 24,
      "color": 4287137928,
      "x": 5757,
      "y": 500,
      "size": 220,
      "index": 0
    },
    {
      "fontId": 24,
      "color": 4287137928,
      "x": 5827,
      "y": 500,
      "size": 220,
      "index": 52
    },
    {
      "fontId": 24,
      "color": 4287137928,
      "x": 5961,
      "y": 500,
      "size": 220,
      "index": 40
    },
    {
      "fontId": 24,
      "color": 4287137928,
      "x": 6127,
      "y": 500,
      "size": 220,
      "index": 37
    },
    {
      "fontId": 24,
      "color": 4287137928,
      "x": 6266,
      "y": 500,
      "size": 220,
      "index": 0
    },
    {
      "fontId": 24,
      "color": 4287137928,
      "x": 6336,
      "y": 500,
      "size": 220,
      "index": 35
    },
    {
      "fontId": 24,
      "color": 4287137928,
      "x": 6490,
      "y": 500,
      "size": 220,
      "index": 41
    },
    {
      "fontId": 24,
      "color": 4287137928,
      "x": 6554,
      "y": 500,
      "size": 220,
      "index": 52
    },
    {
      "fontId": 24,
      "color": 4287137928,
      "x": 6688,
      "y": 500,
      "size": 220,
      "index": 57
    },
    {
      "fontId": 24,
      "color": 4287137928,
      "x": 6823,
      "y": 500,
      "size": 220,
      "index": 0
    },
    {
      "fontId": 24,
      "color": 4287137928,
      "x": 0,
      "y": 800,
      "size": 220,
      "index": 41
    },
    {
      "fontId": 24,
      "color": 4287137928,
      "x": 65,
      "y": 800,
      "size": 220,
      "index": 45
    },
    {
      "fontId": 24,
      "color": 4287137928,
      "x": 255,
      "y": 800,
      "size": 220,
      "index": 45
    },
    {
      "fontId": 24,
      "color": 4287137928,
      "x": 445,
      "y": 800,
      "size": 220,
      "index": 37
    },
    {
      "fontId": 24,
      "color": 4287137928,
      "x": 584,
      "y": 800,
      "size": 220,
      "index": 36
    },
    {
      "fontId": 24,
      "color": 4287137928,
      "x": 753,
      "y": 800,
      "size": 220,
      "index": 41
    },
    {
      "fontId": 24,
      "color": 4287137928,
      "x": 818,
      "y": 800,
      "size": 220,
      "index": 33
    },
    {
      "fontId": 24,
      "color": 4287137928,
      "x": 951,
      "y": 800,
      "size": 220,
      "index": 52
    },
    {
      "fontId": 24,
      "color": 4287137928,
      "x": 1086,
      "y": 800,
      "size": 220,
      "index": 37
    },
    {
      "fontId": 24,
      "color": 4287137928,
      "x": 1225,
      "y": 800,
      "size": 220,
      "index": 44
    },
    {
      "fontId": 24,
      "color": 4287137928,
      "x": 1318,
      "y": 800,
      "size": 220,
      "index": 57
    },
    {
      "fontId": 24,
      "color": 4287137928,
      "x": 1453,
      "y": 800,
      "size": 220,
      "index": 0
    },
    {
      "fontId": 24,
      "color": 4287137928,
      "x": 1523,
      "y": 800,
      "size": 220,
      "index": 53
    },
    {
      "fontId": 24,
      "color": 4287137928,
      "x": 1684,
      "y": 800,
      "size": 220,
      "index": 46
    },
    {
      "fontId": 24,
      "color": 4287137928,
      "x": 1849,
      "y": 800,
      "size": 220,
      "index": 44
    },
    {
      "fontId": 24,
      "color": 4287137928,
      "x": 1971,
      "y": 800,
      "size": 220,
      "index": 37
    },
    {
      "fontId": 24,
      "color": 4287137928,
      "x": 2110,
      "y": 800,
      "size": 220,
      "index": 51
    },
    {
      "fontId": 24,
      "color": 4287137928,
      "x": 2250,
      "y": 800,
      "size": 220,
      "index": 51
    },
    {
      "fontId": 24,
      "color": 4287137928,
      "x": 2389,
      "y": 800,
      "size": 220,
      "index": 0
    },
    {
      "fontId": 24,
      "color": 4287137928,
      "x": 2459,
      "y": 800,
      "size": 220,
      "index": 47
    },
    {
      "fontId": 24,
      "color": 4287137928,
      "x": 2632,
      "y": 800,
      "size": 220,
      "index": 52
    },
    {
      "fontId": 24,
      "color": 4287137928,
      "x": 2767,
      "y": 800,
      "size": 220,
      "index": 40
    },
    {
      "fontId": 24,
      "color": 4287137928,
      "x": 2933,
      "y": 800,
      "size": 220,
      "index": 37
    },
    {
      "fontId": 24,
      "color": 4287137928,
      "x": 3072,
      "y": 800,
      "size": 220,
      "index": 50
    },
    {
      "fontId": 24,
      "color": 4287137928,
      "x": 3216,
      "y": 800,
      "size": 220,
      "index": 55
    },
    {
      "fontId": 24,
      "color": 4287137928,
      "x": 3433,
      "y": 800,
      "size": 220,
      "index": 41
    },
    {
      "fontId": 24,
      "color": 4287137928,
      "x": 3497,
      "y": 800,
      "size": 220,
      "index": 51
    },
    {
      "fontId": 24,
      "color": 4287137928,
      "x": 3637,
      "y": 800,
      "size": 220,
      "index": 37
    },
    {
      "fontId": 24,
      "color": 4287137928,
      "x": 3776,
      "y": 800,
      "size": 220,
      "index": 0
    },
    {
      "fontId": 24,
      "color": 4287137928,
      "x": 3846,
      "y": 800,
      "size": 220,
      "index": 35
    },
    {
      "fontId": 24,
      "color": 4287137928,
      "x": 4000,
      "y": 800,
      "size": 220,
      "index": 50
    },
    {
      "fontId": 24,
      "color": 4287137928,
      "x": 4152,
      "y": 800,
      "size": 220,
      "index": 37
    },
    {
      "fontId": 24,
      "color": 4287137928,
      "x": 4291,
      "y": 800,
      "size": 220,
      "index": 36
    },
    {
      "fontId": 24,
      "color": 4287137928,
      "x": 4460,
      "y": 800,
      "size": 220,
      "index": 37
    },
    {
      "fontId": 24,
      "color": 4287137928,
      "x": 4599,
      "y": 800,
      "size": 220,
      "index": 46
    },
    {
      "fontId": 24,
      "color": 4287137928,
      "x": 4764,
      "y": 800,
      "size": 220,
      "index": 52
    },
    {
      "fontId": 24,
      "color": 4287137928,
      "x": 4898,
      "y": 800,
      "size": 220,
      "index": 41
    },
    {
      "fontId": 24,
      "color": 4287137928,
      "x": 4963,
      "y": 800,
      "size": 220,
      "index": 33
    },
    {
      "fontId": 24,
      "color": 4287137928,
      "x": 5113,
      "y": 800,
      "size": 220,
      "index": 44
    },
    {
      "fontId": 24,
      "color": 4287137928,
      "x": 5236,
      "y": 800,
      "size": 220,
      "index": 37
    },
    {
      "fontId": 24,
      "color": 4287137928,
      "x": 5375,
      "y": 800,
      "size": 220,
      "index": 36
    }
  ],
  "bounds": [-1339, 17, 6821, 806]
}
