{
  "matrix": [1, 0, 0, 1, 0, 0],
  "glyphs": [
    {
      "fontId": 39,
      "color": 4282927176,
      "x": 0,
      "y": 300,
      "size": 400,
      "index": 55
    },
    {
      "fontId": 39,
      "color": 4282927176,
      "x": 378,
      "y": 300,
      "size": 400,
      "index": 72
    },
    {
      "fontId": 39,
      "color": 4282927176,
      "x": 622,
      "y": 300,
      "size": 400,
      "index": 73
    },
    {
      "fontId": 39,
      "color": 4282927176,
      "x": 733,
      "y": 300,
      "size": 400,
      "index": 76
    },
    {
      "fontId": 39,
      "color": 4282927176,
      "x": 844,
      "y": 300,
      "size": 400,
      "index": 69
    },
    {
      "fontId": 39,
      "color": 4282927176,
      "x": 1067,
      "y": 300,
      "size": 400,
      "index": 0
    },
    {
      "fontId": 39,
      "color": 4282927176,
      "x": 1179,
      "y": 300,
      "size": 400,
      "index": 89
    },
    {
      "fontId": 39,
      "color": 4282927176,
      "x": 1402,
      "y": 300,
      "size": 400,
      "index": 79
    },
    {
      "fontId": 39,
      "color": 4282927176,
      "x": 1647,
      "y": 300,
      "size": 400,
      "index": 85
    },
    {
      "fontId": 39,
      "color": 4282927176,
      "x": 1892,
      "y": 300,
      "size": 400,
      "index": 7
    },
    {
      "fontId": 39,
      "color": 4282927176,
      "x": 1987,
      "y": 300,
      "size": 400,
      "index": 82
    },
    {
      "fontId": 39,
      "color": 4282927176,
      "x": 2143,
      "y": 300,
      "size": 400,
      "index": 69
    },
    {
      "fontId": 39,
      "color": 4282927176,
      "x": 2365,
      "y": 300,
      "size": 400,
      "index": 0
    },
    {
      "fontId": 39,
      "color": 4282927176,
      "x": 2477,
      "y": 300,
      "size": 400,
      "index": 87
    },
    {
      "fontId": 39,
      "color": 4282927176,
      "x": 2788,
      "y": 300,
      "size": 400,
      "index": 65
    },
    {
      "fontId": 39,
      "color": 4282927176,
      "x": 3011,
      "y": 300,
      "size": 400,
      "index": 73
    },
    {
      "fontId": 39,
      "color": 4282927176,
      "x": 3123,
      "y": 300,
      "size": 400,
      "index": 84
    },
    {
      "fontId": 39,
      "color": 4282927176,
      "x": 3256,
      "y": 300,
      "size": 400,
      "index": 73
    },
    {
      "fontId": 39,
      "color": 4282927176,
      "x": 3367,
      "y": 300,
      "size": 400,
      "index": 78
    },
    {
      "fontId": 39,
      "color": 4282927176,
      "x": 3611,
      "y": 300,
      "size": 400,
      "index": 71
    },
    {
      "fontId": 39,
      "color": 4282927176,
      "x": 3856,
      "y": 300,
      "size": 400,
      "index": 14
    },
    {
      "fontId": 39,
      "color": 4282927176,
      "x": 3967,
      "y": 300,
      "size": 400,
      "index": 14
    },
    {
      "fontId": 39,
      "color": 4282927176,
      "x": 4078,
      "y": 300,
      "size": 400,
      "index": 14
    }
  ],
  "bounds": [6, -29, 4155, 437]
}
