{
  "matrix": [1, 0, 0, 1, -286, 0],
  "glyphs": [
    {
      "fontId": 88,
      "color": 4288256409,
      "x": 0,
      "y": 180,
      "size": 240,
      "index": 38
    },
    {
      "fontId": 88,
      "color": 4288256409,
      "x": 146,
      "y": 180,
      "size": 240,
      "index": 44
    },
    {
      "fontId": 88,
      "color": 4288256409,
      "x": 279,
      "y": 180,
      "size": 240,
      "index": 47
    },
    {
      "fontId": 88,
      "color": 4288256409,
      "x": 466,
      "y": 180,
      "size": 240,
      "index": 55
    },
    {
      "fontId": 88,
      "color": 4288256409,
      "x": 692,
      "y": 180,
      "size": 240,
      "index": 0
    },
    {
      "fontId": 88,
      "color": 4288256409,
      "x": 758,
      "y": 180,
      "size": 240,
      "index": 50
    },
    {
      "fontId": 88,
      "color": 4288256409,
      "x": 931,
      "y": 180,
      "size": 240,
      "index": 37
    },
    {
      "fontId": 88,
      "color": 4288256409,
      "x": 1091,
      "y": 180,
      "size": 240,
      "index": 33
    },
    {
      "fontId": 88,
      "color": 4288256409,
      "x": 1251,
      "y": 180,
      "size": 240,
      "index": 36
    },
    {
      "fontId": 88,
      "color": 4288256409,
      "x": 1424,
      "y": 180,
      "size": 240,
      "index": 57
    },
    {
      "fontId": 88,
      "color": 4288256409,
      "x": 1580,
      "y": 180,
      "size": 240,
      "index": 0
    },
    {
      "fontId": 88,
      "color": 4288256409,
      "x": 1647,
      "y": 180,
      "size": 240,
      "index": 8
    },
    {
      "fontId": 88,
      "color": 4288256409,
      "x": 1727,
      "y": 180,
      "size": 240,
      "index": 40
    },
    {
      "fontId": 88,
      "color": 4288256409,
      "x": 1900,
      "y": 180,
      "size": 240,
      "index": 47
    },
    {
      "fontId": 88,
      "color": 4288256409,
      "x": 2087,
      "y": 180,
      "size": 240,
      "index": 44
    },
    {
      "fontId": 88,
      "color": 4288256409,
      "x": 2220,
      "y": 180,
      "size": 240,
      "index": 36
    },
    {
      "fontId": 88,
      "color": 4288256409,
      "x": 2394,
      "y": 180,
      "size": 240,
      "index": 0
    },
    {
      "fontId": 88,
      "color": 4288256409,
      "x": 2461,
      "y": 180,
      "size": 240,
      "index": 51
    },
    {
      "fontId": 88,
      "color": 4288256409,
      "x": 2621,
      "y": 180,
      "size": 240,
      "index": 48
    },
    {
      "fontId": 88,
      "color": 4288256409,
      "x": 2763,
      "y": 180,
      "size": 240,
      "index": 33
    },
    {
      "fontId": 88,
      "color": 4288256409,
      "x": 2923,
      "y": 180,
      "size": 240,
      "index": 35
    },
    {
      "fontId": 88,
      "color": 4288256409,
      "x": 3096,
      "y": 180,
      "size": 240,
      "index": 37
    },
    {
      "fontId": 88,
      "color": 4288256409,
      "x": 3256,
      "y": 180,
      "size": 240,
      "index": 0
    },
    {
      "fontId": 88,
      "color": 4288256409,
      "x": 3323,
      "y": 180,
      "size": 240,
      "index": 34
    },
    {
      "fontId": 88,
      "color": 4288256409,
      "x": 3483,
      "y": 180,
      "size": 240,
      "index": 33
    },
    {
      "fontId": 88,
      "color": 4288256409,
      "x": 3643,
      "y": 180,
      "size": 240,
      "index": 50
    },
    {
      "fontId": 88,
      "color": 4288256409,
      "x": 3816,
      "y": 180,
      "size": 240,
      "index": 9
    }
  ],
  "bounds": [-265, -37, 3858, 286]
}
