{
  "matrix": [1, 0, 0, 1, -877, 0],
  "glyphs": [
    {
      "fontId": 24,
      "color": 4292199065,
      "x": 0,
      "y": 400,
      "size": 440,
      "index": 48
    },
    {
      "fontId": 24,
      "color": 4292199065,
      "x": 265,
      "y": 400,
      "size": 440,
      "index": 44
    },
    {
      "fontId": 24,
      "color": 4292199065,
      "x": 510,
      "y": 400,
      "size": 440,
      "index": 37
    },
    {
      "fontId": 24,
      "color": 4292199065,
      "x": 788,
      "y": 400,
      "size": 440,
      "index": 33
    },
    {
      "fontId": 24,
      "color": 4292199065,
      "x": 1089,
      "y": 400,
      "size": 440,
      "index": 51
    },
    {
      "fontId": 24,
      "color": 4292199065,
      "x": 1368,
      "y": 400,
      "size": 440,
      "index": 37
    },
    {
      "fontId": 24,
      "color": 4292199065,
      "x": 1646,
      "y": 400,
      "size": 440,
      "index": 0
    },
    {
      "fontId": 24,
      "color": 4292199065,
      "x": 1786,
      "y": 400,
      "size": 440,
      "index": 55
    },
    {
      "fontId": 24,
      "color": 4292199065,
      "x": 2221,
      "y": 400,
      "size": 440,
      "index": 37
    },
    {
      "fontId": 24,
      "color": 4292199065,
      "x": 2499,
      "y": 400,
      "size": 440,
      "index": 44
    },
    {
      "fontId": 24,
      "color": 4292199065,
      "x": 2744,
      "y": 400,
      "size": 440,
      "index": 35
    },
    {
      "fontId": 24,
      "color": 4292199065,
      "x": 3051,
      "y": 400,
      "size": 440,
      "index": 47
    },
    {
      "fontId": 24,
      "color": 4292199065,
      "x": 3398,
      "y": 400,
      "size": 440,
      "index": 45
    },
    {
      "fontId": 24,
      "color": 4292199065,
      "x": 3778,
      "y": 400,
      "size": 440,
      "index": 37
    },
    {
      "fontId": 24,
      "color": 4292199065,
      "x": 4056,
      "y": 400,
      "size": 440,
      "index": 0
    },
    {
      "fontId": 24,
      "color": 4292199065,
      "x": 4196,
      "y": 400,
      "size": 440,
      "index": 50
    },
    {
      "fontId": 24,
      "color": 4292199065,
      "x": 4502,
      "y": 400,
      "size": 440,
      "index": 53
    },
    {
      "fontId": 24,
      "color": 4292199065,
      "x": 4824,
      "y": 400,
      "size": 440,
      "index": 46
    },
    {
      "fontId": 24,
      "color": 4292199065,
      "x": 5153,
      "y": 400,
      "size": 440,
      "index": 46
    },
    {
      "fontId": 24,
      "color": 4292199065,
      "x": 5482,
      "y": 400,
      "size": 440,
      "index": 37
    },
    {
      "fontId": 24,
      "color": 4292199065,
      "x": 5760,
      "y": 400,
      "size": 440,
      "index": 50
    }
  ],
  "bounds": [-834, 53, 6011, 374]
}
