{
  "matrix": [1, 0, 0, 1, 0, 0],
  "glyphs": [
    {
      "fontId": 39,
      "color": 4284913920,
      "x": 0,
      "y": 800,
      "size": 1040,
      "index": 45
    },
    {
      "fontId": 39,
      "color": 4284913920,
      "x": 866,
      "y": 800,
      "size": 1040,
      "index": 85
    },
    {
      "fontId": 39,
      "color": 4284913920,
      "x": 1502,
      "y": 800,
      "size": 1040,
      "index": 76
    },
    {
      "fontId": 39,
      "color": 4284913920,
      "x": 1791,
      "y": 800,
      "size": 1040,
      "index": 84
    },
    {
      "fontId": 39,
      "color": 4284913920,
      "x": 2137,
      "y": 800,
      "size": 1040,
      "index": 73
    },
    {
      "fontId": 39,
      "color": 4284913920,
      "x": 2426,
      "y": 800,
      "size": 1040,
      "index": 80
    },
    {
      "fontId": 39,
      "color": 4284913920,
      "x": 3061,
      "y": 800,
      "size": 1040,
      "index": 76
    },
    {
      "fontId": 39,
      "color": 4284913920,
      "x": 3350,
      "y": 800,
      "size": 1040,
      "index": 65
    },
    {
      "fontId": 39,
      "color": 4284913920,
      "x": 3928,
      "y": 800,
      "size": 1040,
      "index": 89
    },
    {
      "fontId": 39,
      "color": 4284913920,
      "x": 4507,
      "y": 800,
      "size": 1040,
      "index": 69
    },
    {
      "fontId": 39,
      "color": 4284913920,
      "x": 5086,
      "y": 800,
      "size": 1040,
      "index": 82
    }
  ],
  "bounds": [77, 8, 5399, 1040]
}
